buffer_matcher/__init__.py
buffer_matcher/base.py
buffer_matcher/dynamic.py
buffer_matcher/simple.py
buffer_matcher/static.py
buffer_matcher-0.1.1.dist-info/LICENSE
buffer_matcher-0.1.1.dist-info/METADATA
buffer_matcher-0.1.1.dist-info/WHEEL
buffer_matcher-0.1.1.dist-info/top_level.txt
buffer_matcher-0.1.1.dist-info/RECORD
