Metadata-Version: 2.1
Name: buffer-matcher
Version: 0.1.1
Summary: More efficiently match bytes using memoryviews to prevent copying
Author: Shae.c32
Project-URL: Homepage, https://codeberg.org/Shae/BufferMatcher
Project-URL: Issues, https://codeberg.org/Shae/BufferMatcher/issues
Keywords: buffer,match,memory,view
Classifier: Development Status :: 4 - Beta
Classifier: Intended Audience :: Developers
Classifier: License :: OSI Approved :: Apache Software License
Classifier: Natural Language :: English
Classifier: Operating System :: OS Independent
Classifier: Programming Language :: Python :: 3
Classifier: Topic :: Software Development :: Libraries :: Python Modules
Classifier: Topic :: Text Processing
Classifier: Topic :: Utilities
Classifier: Typing :: Typed
Requires-Python: >=3.12
License-File: LICENSE
